sapientml_preprocess/__init__.py
sapientml_preprocess/generator.py
sapientml_preprocess/params.py
sapientml_preprocess/templates/drop_one_value_columns.py.jinja
sapientml_preprocess/templates/handle_inf_columns.py.jinja
sapientml_preprocess/templates/handle_iterable_values.py.jinja
sapientml_preprocess/templates/handle_japanese_text.py.jinja
sapientml_preprocess/templates/handle_mixed_typed_columns.py.jinja
sapientml_preprocess/templates/rename_columns.py.jinja
sapientml_preprocess-0.3.6.post0.dist-info/LICENSE
sapientml_preprocess-0.3.6.post0.dist-info/METADATA
sapientml_preprocess-0.3.6.post0.dist-info/WHEEL
sapientml_preprocess-0.3.6.post0.dist-info/entry_points.txt
sapientml_preprocess-0.3.6.post0.dist-info/RECORD
