Metadata-Version: 2.1
Name: sapientml-preprocess
Version: 0.3.6.post0
Summary: A SapientML plugin of preprocess CodeBlockGenerator
License: Apache-2.0
Author: The SapientML Authors
Maintainer: Kosaku Kimura
Maintainer-email: kimura.kosaku@fujitsu.com
Requires-Python: >=3.10,<3.13
Classifier: License :: OSI Approved :: Apache Software License
Classifier: Programming Language :: Python :: 3
Classifier: Programming Language :: Python :: 3.10
Classifier: Programming Language :: Python :: 3.11
Classifier: Programming Language :: Python :: 3.12
Requires-Dist: fasttext-wheel (>=0.9.2,<0.10.0)
Requires-Dist: ipadic (>=1.0.0,<2.0.0)
Requires-Dist: jinja2 (>=3.1.2,<4.0.0)
Requires-Dist: mecab-python3 (>=1.0.6,<2.0.0)
Requires-Dist: numba (>=0.57.1,<0.60.0)
Requires-Dist: requests (>=2.31.0,<3.0.0)
Requires-Dist: sapientml
